{
  "mode": "pre",
  "tag": "three",
  "initialVersions": {
    "hello-world-benchmark": "0.13.11",
    "@graphql-yoga/e2e-testing": "0.0.0",
    "example-apollo-federation": "0.0.1",
    "apollo-federation-gateway-with-yoga": "0.13.11",
    "apollo-subgraph-with-yoga": "0.13.11",
    "example-aws-lambda": "0.0.0",
    "graphql-lambda": "0.13.11",
    "example-azure-function": "0.0.0",
    "example-bun": "0.0.0",
    "cloudflare-advanced": "0.7.10",
    "cloudflare": "0.4.10",
    "example-defer-stream": "0.13.6",
    "example-error-handling": "0.13.6",
    "example-express": "0.13.6",
    "example-fastify": "0.13.6",
    "example-fastify-modules": "0.13.6",
    "example-file-upload": "0.13.11",
    "example-file-upload-nextjs-pothos": "0.11.11",
    "example-file-upload-nexus": "0.13.11",
    "example-generic-auth": "1.9.11",
    "example-graphql-armor": "0.0.5",
    "example-graphql-config": "0.13.6",
    "example-graphql-ws": "0.10.11",
    "hackernews": "1.13.11",
    "example-hello-world": "0.13.11",
    "example-issue-template": "1.13.11",
    "example-koa": "0.13.6",
    "example-live-query": "0.13.11",
    "example-netlify-edge": "0.0.0",
    "example-nextjs": "0.13.11",
    "example-nextjs-auth": "0.13.11",
    "example-node-esm": "0.12.11",
    "example-redis-pub-sub": "0.1.11",
    "example-service-worker": "0.12.3",
    "example-subscriptions": "0.13.6",
    "example-sveltekit": "0.12.3",
    "@graphql-yoga/apollo-link": "0.0.0",
    "@graphql-yoga/urql-exchange": "0.0.0",
    "@graphql-yoga/common": "2.12.10",
    "@graphql-yoga/redis-event-target": "0.1.3",
    "@graphql-yoga/typed-event-target": "0.1.1",
    "@graphql-yoga/graphiql": "2.4.2",
    "graphql-yoga": "2.13.11",
    "@graphql-yoga/node": "2.13.11",
    "@graphql-yoga/plugin-apollo-inline-trace": "0.0.0",
    "@graphql-yoga/plugin-apq": "0.0.0",
    "@graphql-yoga/plugin-persisted-operations": "0.0.0",
    "@graphql-yoga/plugin-response-cache": "0.0.0",
    "@graphql-yoga/render-graphiql": "2.13.10",
    "@graphql-yoga/subscription": "2.2.3",
    "website": "0.0.0",
    "example-deno": "0.0.0",
    "example-node-ts": "1.0.0",
    "example-pothos": "1.0.0",
    "@graphql-yoga/plugin-prometheus": "0.0.0",
    "@graphql-yoga/plugin-defer-stream": "0.0.0"
  },
  "changesets": [
    "breezy-ads-walk",
    "bright-wasps-boil",
    "chilly-rats-marry",
    "chilly-windows-happen",
    "cuddly-lamps-know",
    "curvy-oranges-heal",
    "curvy-sloths-move",
    "dirty-pillows-tap",
    "eight-eyes-nail",
    "fast-coats-explode",
    "fifty-elephants-provide",
    "grumpy-kangaroos-tell",
    "happy-dolls-shout",
    "healthy-lizards-walk",
    "healthy-waves-sing",
    "hungry-knives-raise",
    "long-ears-brake",
    "metal-maps-dream",
    "more-accept-headers",
    "nine-brooms-cough",
    "orange-paws-tease",
    "pretty-cycles-wait",
    "red-coins-develop",
    "rotten-ghosts-design",
    "seven-tomatoes-invent",
    "silent-ants-vanish",
    "slow-wasps-hide",
    "smart-pens-compete",
    "sour-apricots-move",
    "spicy-mails-judge",
    "spotty-crews-poke",
    "strong-peas-exercise",
    "sweet-paws-kiss",
    "tall-paws-do",
    "ten-panthers-cover",
    "thirty-lobsters-study",
    "twenty-poets-prove"
  ]
}
